karton_asciimagic-1.2.0-nspkg.pth
karton/asciimagic/__init__.py
karton/asciimagic/__main__.py
karton/asciimagic/__version__.py
karton/asciimagic/asciiclassifier.py
karton/asciimagic/asciimagic.py
karton/asciimagic/decoders.py
karton_asciimagic-1.2.0.dist-info/LICENSE
karton_asciimagic-1.2.0.dist-info/METADATA
karton_asciimagic-1.2.0.dist-info/WHEEL
karton_asciimagic-1.2.0.dist-info/entry_points.txt
karton_asciimagic-1.2.0.dist-info/namespace_packages.txt
karton_asciimagic-1.2.0.dist-info/top_level.txt
karton_asciimagic-1.2.0.dist-info/RECORD
