Metadata-Version: 2.1
Name: karton-asciimagic
Version: 1.2.0
Summary: Various encoders for ascii-encoded executables for Karton framework
Home-page: https://github.com/CERT-Polska/karton-asciimagic/
License: UNKNOWN
Platform: UNKNOWN
Classifier: Programming Language :: Python
Classifier: Operating System :: OS Independent
Requires-Dist: karton-core (<6.0.0,>=5.0.0)
